setup.py
MinecraftSkyblockAPI/__init__.py
MinecraftSkyblockAPI/minecraftTHEapi.py
MinecraftSkyblockAPI.egg-info/PKG-INFO
MinecraftSkyblockAPI.egg-info/SOURCES.txt
MinecraftSkyblockAPI.egg-info/dependency_links.txt
MinecraftSkyblockAPI.egg-info/requires.txt
MinecraftSkyblockAPI.egg-info/top_level.txt