Metadata-Version: 2.1
Name: MinecraftSkyblockAPI
Version: 0.2.3
Summary: minecraft api
